examples/__init__.py
examples/basis.py
python_dependency_resolver/__init__.py
python_dependency_resolver/exceptions.py
tests/__init__.py
python_dependency_resolver-1.0.4.dist-info/LICENSE
python_dependency_resolver-1.0.4.dist-info/METADATA
python_dependency_resolver-1.0.4.dist-info/WHEEL
python_dependency_resolver-1.0.4.dist-info/top_level.txt
python_dependency_resolver-1.0.4.dist-info/RECORD
