Metadata-Version: 2.1
Name: python-dependency-resolver
Version: 1.0.4
Summary: UNKNOWN
Home-page: https://anthonykgross.fr/python-dependency-resolver/
Author: Anthony K GROSS
Author-email: anthony.k.gross@gmail.com
License: UNKNOWN
Project-URL: Documentation, https://anthonykgross.fr/python-dependency-resolver/
Project-URL: Source, https://github.com/anthonykgross/python-dependency-resolver/
Platform: UNKNOWN
Classifier: Programming Language :: Python :: 3
Classifier: License :: OSI Approved :: MIT License
Classifier: Operating System :: OS Independent
Requires-Python: >=3.8
License-File: LICENSE
